CHANGELOG.md
LICENSE
MANIFEST.in
README.md
TODO.md
requirements.txt
setup.py
flask_neglog/__init__.py
flask_neglog/extension.py
flask_neglog/logger.py
flask_neglog/utils.py
flask_neglog.egg-info/PKG-INFO
flask_neglog.egg-info/SOURCES.txt
flask_neglog.egg-info/dependency_links.txt
flask_neglog.egg-info/top_level.txt
test/__init__.py
test/test_flask_neglog.py